drf_yasg_examples.py
drf_yasg_examples-0.1.1.dist-info/LICENSE
drf_yasg_examples-0.1.1.dist-info/WHEEL
drf_yasg_examples-0.1.1.dist-info/METADATA
drf_yasg_examples-0.1.1.dist-info/RECORD
